src/mhw_detect/cut/__init__.py
src/mhw_detect/cut/cut.ipynb
src/mhw_detect/cut/cut.py
src/mhw_detect/detection/__init__.py
src/mhw_detect/detection/detect.py
src/mhw_detect/detection/marineHeatWavesOpt.py
src/mhw_detect/detection/mhw.py
src/mhw_detect/detection/optims.py
src/mhw_detect/detection/parser.py
mhw_detect-0.2.4.dist-info/entry_points.txt
mhw_detect-0.2.4.dist-info/METADATA
mhw_detect-0.2.4.dist-info/WHEEL
mhw_detect-0.2.4.dist-info/RECORD
