Metadata-Version: 2.1
Name: mhw-detect
Version: 0.2.4
Summary: Fast marine heatwaves and extrem events detector based on https://github.com/ecjoliver/marineHeatWaves
Author: John Brouillet
Requires-Python: >=3.8,<3.12
Classifier: Programming Language :: Python :: 3
Classifier: Programming Language :: Python :: 3.8
Classifier: Programming Language :: Python :: 3.9
Classifier: Programming Language :: Python :: 3.10
Classifier: Programming Language :: Python :: 3.11
Requires-Dist: click (>=8.1.3)
Requires-Dist: dask (>=2021.10.0)
Requires-Dist: netCDF4 (>=1.5.7)
Requires-Dist: numba (>=0.54.1)
Requires-Dist: numpy (>=1.20.3)
Requires-Dist: pandas (>=1.3.5)
Requires-Dist: pyarrow (>=11.0.0,<12.0.0)
Requires-Dist: scipy (>=1.7.3)
Requires-Dist: xarray (>=2022.6.0)
